[
   {"value": 7149007, "isPrime": true}
   {"value": 7149013, "isPrime": true}
   {"value": 7149019, "isPrime": true}
   {"value": 7149041, "isPrime": true}
   {"value": 7149049, "isPrime": true}
   {"value": 7149053, "isPrime": true}
   {"value": 7149059, "isPrime": true}
   {"value": 7149097, "isPrime": true}
   {"value": 7149143, "isPrime": true}
   {"value": 7149161, "isPrime": true}
   {"value": 7149193, "isPrime": true}
   {"value": 7149209, "isPrime": true}
   {"value": 7149221, "isPrime": true}
   {"value": 7149227, "isPrime": true}
   {"value": 7149239, "isPrime": true}
   {"value": 7149253, "isPrime": true}
   {"value": 7149257, "isPrime": true}
   {"value": 7149271, "isPrime": true}
   {"value": 7149277, "isPrime": true}
   {"value": 7149347, "isPrime": true}
   {"value": 7149349, "isPrime": true}
   {"value": 7149353, "isPrime": true}
   {"value": 7149361, "isPrime": true}
   {"value": 7149379, "isPrime": true}
   {"value": 7149403, "isPrime": true}
   {"value": 7149407, "isPrime": true}
   {"value": 7149409, "isPrime": true}
   {"value": 7149413, "isPrime": true}
   {"value": 7149433, "isPrime": true}
   {"value": 7149449, "isPrime": true}
   {"value": 7149463, "isPrime": true}
   {"value": 7149479, "isPrime": true}
   {"value": 7149497, "isPrime": true}
   {"value": 7149509, "isPrime": true}
   {"value": 7149511, "isPrime": true}
   {"value": 7149521, "isPrime": true}
   {"value": 7149523, "isPrime": true}
   {"value": 7149533, "isPrime": true}
   {"value": 7149551, "isPrime": true}
   {"value": 7149557, "isPrime": true}
   {"value": 7149559, "isPrime": true}
   {"value": 7149563, "isPrime": true}
   {"value": 7149581, "isPrime": true}
   {"value": 7149589, "isPrime": true}
   {"value": 7149599, "isPrime": true}
   {"value": 7149601, "isPrime": true}
   {"value": 7149613, "isPrime": true}
   {"value": 7149617, "isPrime": true}
   {"value": 7149641, "isPrime": true}
   {"value": 7149671, "isPrime": true}
   {"value": 7149677, "isPrime": true}
   {"value": 7149691, "isPrime": true}
   {"value": 7149713, "isPrime": true}
   {"value": 7149731, "isPrime": true}
   {"value": 7149733, "isPrime": true}
   {"value": 7149761, "isPrime": true}
   {"value": 7149767, "isPrime": true}
   {"value": 7149799, "isPrime": true}
   {"value": 7149811, "isPrime": true}
   {"value": 7149817, "isPrime": true}
   {"value": 7149823, "isPrime": true}
   {"value": 7149827, "isPrime": true}
   {"value": 7149829, "isPrime": true}
   {"value": 7149841, "isPrime": true}
   {"value": 7149851, "isPrime": true}
   {"value": 7149899, "isPrime": true}
   {"value": 7149907, "isPrime": true}
   {"value": 7149929, "isPrime": true}
   {"value": 7149943, "isPrime": true}
   {"value": 7149959, "isPrime": true}
   {"value": 7149971, "isPrime": true}
   {"value": 7149983, "isPrime": true}
]
