[
   {"value": 7329013, "isPrime": true}
   {"value": 7329031, "isPrime": true}
   {"value": 7329059, "isPrime": true}
   {"value": 7329073, "isPrime": true}
   {"value": 7329097, "isPrime": true}
   {"value": 7329103, "isPrime": true}
   {"value": 7329107, "isPrime": true}
   {"value": 7329109, "isPrime": true}
   {"value": 7329121, "isPrime": true}
   {"value": 7329131, "isPrime": true}
   {"value": 7329139, "isPrime": true}
   {"value": 7329151, "isPrime": true}
   {"value": 7329163, "isPrime": true}
   {"value": 7329167, "isPrime": true}
   {"value": 7329169, "isPrime": true}
   {"value": 7329173, "isPrime": true}
   {"value": 7329181, "isPrime": true}
   {"value": 7329187, "isPrime": true}
   {"value": 7329209, "isPrime": true}
   {"value": 7329229, "isPrime": true}
   {"value": 7329241, "isPrime": true}
   {"value": 7329247, "isPrime": true}
   {"value": 7329251, "isPrime": true}
   {"value": 7329263, "isPrime": true}
   {"value": 7329271, "isPrime": true}
   {"value": 7329277, "isPrime": true}
   {"value": 7329313, "isPrime": true}
   {"value": 7329353, "isPrime": true}
   {"value": 7329359, "isPrime": true}
   {"value": 7329403, "isPrime": true}
   {"value": 7329407, "isPrime": true}
   {"value": 7329409, "isPrime": true}
   {"value": 7329461, "isPrime": true}
   {"value": 7329473, "isPrime": true}
   {"value": 7329503, "isPrime": true}
   {"value": 7329559, "isPrime": true}
   {"value": 7329587, "isPrime": true}
   {"value": 7329593, "isPrime": true}
   {"value": 7329613, "isPrime": true}
   {"value": 7329653, "isPrime": true}
   {"value": 7329659, "isPrime": true}
   {"value": 7329661, "isPrime": true}
   {"value": 7329677, "isPrime": true}
   {"value": 7329713, "isPrime": true}
   {"value": 7329719, "isPrime": true}
   {"value": 7329731, "isPrime": true}
   {"value": 7329743, "isPrime": true}
   {"value": 7329761, "isPrime": true}
   {"value": 7329769, "isPrime": true}
   {"value": 7329781, "isPrime": true}
   {"value": 7329793, "isPrime": true}
   {"value": 7329809, "isPrime": true}
   {"value": 7329841, "isPrime": true}
   {"value": 7329851, "isPrime": true}
   {"value": 7329853, "isPrime": true}
   {"value": 7329899, "isPrime": true}
   {"value": 7329937, "isPrime": true}
   {"value": 7329961, "isPrime": true}
   {"value": 7329967, "isPrime": true}
   {"value": 7329977, "isPrime": true}
   {"value": 7329989, "isPrime": true}
]
