[
   {"value": 7461007, "isPrime": true}
   {"value": 7461017, "isPrime": true}
   {"value": 7461019, "isPrime": true}
   {"value": 7461029, "isPrime": true}
   {"value": 7461031, "isPrime": true}
   {"value": 7461043, "isPrime": true}
   {"value": 7461073, "isPrime": true}
   {"value": 7461089, "isPrime": true}
   {"value": 7461101, "isPrime": true}
   {"value": 7461121, "isPrime": true}
   {"value": 7461127, "isPrime": true}
   {"value": 7461169, "isPrime": true}
   {"value": 7461193, "isPrime": true}
   {"value": 7461211, "isPrime": true}
   {"value": 7461247, "isPrime": true}
   {"value": 7461299, "isPrime": true}
   {"value": 7461329, "isPrime": true}
   {"value": 7461343, "isPrime": true}
   {"value": 7461353, "isPrime": true}
   {"value": 7461371, "isPrime": true}
   {"value": 7461397, "isPrime": true}
   {"value": 7461401, "isPrime": true}
   {"value": 7461469, "isPrime": true}
   {"value": 7461479, "isPrime": true}
   {"value": 7461491, "isPrime": true}
   {"value": 7461527, "isPrime": true}
   {"value": 7461529, "isPrime": true}
   {"value": 7461557, "isPrime": true}
   {"value": 7461563, "isPrime": true}
   {"value": 7461569, "isPrime": true}
   {"value": 7461599, "isPrime": true}
   {"value": 7461611, "isPrime": true}
   {"value": 7461647, "isPrime": true}
   {"value": 7461653, "isPrime": true}
   {"value": 7461667, "isPrime": true}
   {"value": 7461677, "isPrime": true}
   {"value": 7461689, "isPrime": true}
   {"value": 7461697, "isPrime": true}
   {"value": 7461757, "isPrime": true}
   {"value": 7461761, "isPrime": true}
   {"value": 7461763, "isPrime": true}
   {"value": 7461781, "isPrime": true}
   {"value": 7461809, "isPrime": true}
   {"value": 7461847, "isPrime": true}
   {"value": 7461869, "isPrime": true}
   {"value": 7461941, "isPrime": true}
   {"value": 7461943, "isPrime": true}
   {"value": 7461983, "isPrime": true}
]
