[
   {"value": 8260009, "isPrime": true}
   {"value": 8260019, "isPrime": true}
   {"value": 8260027, "isPrime": true}
   {"value": 8260033, "isPrime": true}
   {"value": 8260039, "isPrime": true}
   {"value": 8260051, "isPrime": true}
   {"value": 8260061, "isPrime": true}
   {"value": 8260067, "isPrime": true}
   {"value": 8260073, "isPrime": true}
   {"value": 8260097, "isPrime": true}
   {"value": 8260111, "isPrime": true}
   {"value": 8260123, "isPrime": true}
   {"value": 8260127, "isPrime": true}
   {"value": 8260201, "isPrime": true}
   {"value": 8260223, "isPrime": true}
   {"value": 8260261, "isPrime": true}
   {"value": 8260267, "isPrime": true}
   {"value": 8260271, "isPrime": true}
   {"value": 8260277, "isPrime": true}
   {"value": 8260309, "isPrime": true}
   {"value": 8260327, "isPrime": true}
   {"value": 8260337, "isPrime": true}
   {"value": 8260339, "isPrime": true}
   {"value": 8260349, "isPrime": true}
   {"value": 8260387, "isPrime": true}
   {"value": 8260397, "isPrime": true}
   {"value": 8260403, "isPrime": true}
   {"value": 8260433, "isPrime": true}
   {"value": 8260457, "isPrime": true}
   {"value": 8260489, "isPrime": true}
   {"value": 8260493, "isPrime": true}
   {"value": 8260501, "isPrime": true}
   {"value": 8260513, "isPrime": true}
   {"value": 8260523, "isPrime": true}
   {"value": 8260541, "isPrime": true}
   {"value": 8260547, "isPrime": true}
   {"value": 8260619, "isPrime": true}
   {"value": 8260627, "isPrime": true}
   {"value": 8260643, "isPrime": true}
   {"value": 8260667, "isPrime": true}
   {"value": 8260669, "isPrime": true}
   {"value": 8260697, "isPrime": true}
   {"value": 8260711, "isPrime": true}
   {"value": 8260723, "isPrime": true}
   {"value": 8260771, "isPrime": true}
   {"value": 8260799, "isPrime": true}
   {"value": 8260807, "isPrime": true}
   {"value": 8260823, "isPrime": true}
   {"value": 8260829, "isPrime": true}
   {"value": 8260843, "isPrime": true}
   {"value": 8260871, "isPrime": true}
   {"value": 8260873, "isPrime": true}
   {"value": 8260883, "isPrime": true}
   {"value": 8260919, "isPrime": true}
   {"value": 8260937, "isPrime": true}
   {"value": 8260939, "isPrime": true}
   {"value": 8260943, "isPrime": true}
   {"value": 8260961, "isPrime": true}
   {"value": 8260999, "isPrime": true}
]
