[
   {"value": 8920003, "isPrime": true},
   {"value": 8920027, "isPrime": true},
   {"value": 8920031, "isPrime": true},
   {"value": 8920039, "isPrime": true},
   {"value": 8920057, "isPrime": true},
   {"value": 8920069, "isPrime": true},
   {"value": 8920097, "isPrime": true},
   {"value": 8920103, "isPrime": true},
   {"value": 8920123, "isPrime": true},
   {"value": 8920129, "isPrime": true},
   {"value": 8920141, "isPrime": true},
   {"value": 8920147, "isPrime": true},
   {"value": 8920169, "isPrime": true},
   {"value": 8920181, "isPrime": true},
   {"value": 8920199, "isPrime": true},
   {"value": 8920201, "isPrime": true},
   {"value": 8920243, "isPrime": true},
   {"value": 8920277, "isPrime": true},
   {"value": 8920279, "isPrime": true},
   {"value": 8920321, "isPrime": true},
   {"value": 8920337, "isPrime": true},
   {"value": 8920391, "isPrime": true},
   {"value": 8920403, "isPrime": true},
   {"value": 8920423, "isPrime": true},
   {"value": 8920433, "isPrime": true},
   {"value": 8920463, "isPrime": true},
   {"value": 8920489, "isPrime": true},
   {"value": 8920517, "isPrime": true},
   {"value": 8920531, "isPrime": true},
   {"value": 8920537, "isPrime": true},
   {"value": 8920543, "isPrime": true},
   {"value": 8920547, "isPrime": true},
   {"value": 8920567, "isPrime": true},
   {"value": 8920609, "isPrime": true},
   {"value": 8920649, "isPrime": true},
   {"value": 8920679, "isPrime": true},
   {"value": 8920687, "isPrime": true},
   {"value": 8920693, "isPrime": true},
   {"value": 8920721, "isPrime": true},
   {"value": 8920729, "isPrime": true},
   {"value": 8920753, "isPrime": true},
   {"value": 8920763, "isPrime": true},
   {"value": 8920771, "isPrime": true},
   {"value": 8920783, "isPrime": true},
   {"value": 8920817, "isPrime": true},
   {"value": 8920837, "isPrime": true},
   {"value": 8920853, "isPrime": true},
   {"value": 8920867, "isPrime": true},
   {"value": 8920889, "isPrime": true},
   {"value": 8920913, "isPrime": true},
   {"value": 8920921, "isPrime": true},
   {"value": 8920927, "isPrime": true},
   {"value": 8920939, "isPrime": true},
   {"value": 8920943, "isPrime": true},
   {"value": 8920981, "isPrime": true},
   {"value": 8920999, "isPrime": true}
]
