[
   {"value": 11218013, "isPrime": true},
   {"value": 11218049, "isPrime": true},
   {"value": 11218057, "isPrime": true},
   {"value": 11218069, "isPrime": true},
   {"value": 11218073, "isPrime": true},
   {"value": 11218093, "isPrime": true},
   {"value": 11218111, "isPrime": true},
   {"value": 11218117, "isPrime": true},
   {"value": 11218127, "isPrime": true},
   {"value": 11218159, "isPrime": true},
   {"value": 11218169, "isPrime": true},
   {"value": 11218177, "isPrime": true},
   {"value": 11218211, "isPrime": true},
   {"value": 11218217, "isPrime": true},
   {"value": 11218219, "isPrime": true},
   {"value": 11218231, "isPrime": true},
   {"value": 11218241, "isPrime": true},
   {"value": 11218247, "isPrime": true},
   {"value": 11218253, "isPrime": true},
   {"value": 11218261, "isPrime": true},
   {"value": 11218267, "isPrime": true},
   {"value": 11218343, "isPrime": true},
   {"value": 11218349, "isPrime": true},
   {"value": 11218357, "isPrime": true},
   {"value": 11218367, "isPrime": true},
   {"value": 11218369, "isPrime": true},
   {"value": 11218381, "isPrime": true},
   {"value": 11218397, "isPrime": true},
   {"value": 11218433, "isPrime": true},
   {"value": 11218439, "isPrime": true},
   {"value": 11218463, "isPrime": true},
   {"value": 11218469, "isPrime": true},
   {"value": 11218483, "isPrime": true},
   {"value": 11218489, "isPrime": true},
   {"value": 11218517, "isPrime": true},
   {"value": 11218573, "isPrime": true},
   {"value": 11218577, "isPrime": true},
   {"value": 11218601, "isPrime": true},
   {"value": 11218609, "isPrime": true},
   {"value": 11218619, "isPrime": true},
   {"value": 11218631, "isPrime": true},
   {"value": 11218633, "isPrime": true},
   {"value": 11218637, "isPrime": true},
   {"value": 11218643, "isPrime": true},
   {"value": 11218651, "isPrime": true},
   {"value": 11218661, "isPrime": true},
   {"value": 11218663, "isPrime": true},
   {"value": 11218667, "isPrime": true},
   {"value": 11218699, "isPrime": true},
   {"value": 11218747, "isPrime": true},
   {"value": 11218751, "isPrime": true},
   {"value": 11218763, "isPrime": true},
   {"value": 11218769, "isPrime": true},
   {"value": 11218787, "isPrime": true},
   {"value": 11218811, "isPrime": true},
   {"value": 11218813, "isPrime": true},
   {"value": 11218817, "isPrime": true},
   {"value": 11218841, "isPrime": true},
   {"value": 11218849, "isPrime": true},
   {"value": 11218903, "isPrime": true},
   {"value": 11218943, "isPrime": true},
   {"value": 11218981, "isPrime": true}
]
