[
   {"value": 11604011, "isPrime": true},
   {"value": 11604059, "isPrime": true},
   {"value": 11604067, "isPrime": true},
   {"value": 11604077, "isPrime": true},
   {"value": 11604097, "isPrime": true},
   {"value": 11604101, "isPrime": true},
   {"value": 11604113, "isPrime": true},
   {"value": 11604119, "isPrime": true},
   {"value": 11604161, "isPrime": true},
   {"value": 11604181, "isPrime": true},
   {"value": 11604211, "isPrime": true},
   {"value": 11604223, "isPrime": true},
   {"value": 11604227, "isPrime": true},
   {"value": 11604239, "isPrime": true},
   {"value": 11604247, "isPrime": true},
   {"value": 11604277, "isPrime": true},
   {"value": 11604283, "isPrime": true},
   {"value": 11604301, "isPrime": true},
   {"value": 11604317, "isPrime": true},
   {"value": 11604407, "isPrime": true},
   {"value": 11604409, "isPrime": true},
   {"value": 11604413, "isPrime": true},
   {"value": 11604431, "isPrime": true},
   {"value": 11604449, "isPrime": true},
   {"value": 11604451, "isPrime": true},
   {"value": 11604473, "isPrime": true},
   {"value": 11604487, "isPrime": true},
   {"value": 11604493, "isPrime": true},
   {"value": 11604503, "isPrime": true},
   {"value": 11604521, "isPrime": true},
   {"value": 11604559, "isPrime": true},
   {"value": 11604563, "isPrime": true},
   {"value": 11604577, "isPrime": true},
   {"value": 11604583, "isPrime": true},
   {"value": 11604589, "isPrime": true},
   {"value": 11604613, "isPrime": true},
   {"value": 11604617, "isPrime": true},
   {"value": 11604623, "isPrime": true},
   {"value": 11604631, "isPrime": true},
   {"value": 11604641, "isPrime": true},
   {"value": 11604647, "isPrime": true},
   {"value": 11604653, "isPrime": true},
   {"value": 11604661, "isPrime": true},
   {"value": 11604683, "isPrime": true},
   {"value": 11604689, "isPrime": true},
   {"value": 11604731, "isPrime": true},
   {"value": 11604743, "isPrime": true},
   {"value": 11604767, "isPrime": true},
   {"value": 11604779, "isPrime": true},
   {"value": 11604781, "isPrime": true},
   {"value": 11604787, "isPrime": true},
   {"value": 11604793, "isPrime": true},
   {"value": 11604809, "isPrime": true},
   {"value": 11604821, "isPrime": true},
   {"value": 11604841, "isPrime": true},
   {"value": 11604871, "isPrime": true},
   {"value": 11604889, "isPrime": true},
   {"value": 11604893, "isPrime": true},
   {"value": 11604913, "isPrime": true},
   {"value": 11604919, "isPrime": true},
   {"value": 11604937, "isPrime": true},
   {"value": 11604941, "isPrime": true},
   {"value": 11604947, "isPrime": true},
   {"value": 11604961, "isPrime": true}
]
