[
   {"value": 693019, "isPrime": true},
   {"value": 693037, "isPrime": true},
   {"value": 693041, "isPrime": true},
   {"value": 693061, "isPrime": true},
   {"value": 693079, "isPrime": true},
   {"value": 693089, "isPrime": true},
   {"value": 693097, "isPrime": true},
   {"value": 693103, "isPrime": true},
   {"value": 693127, "isPrime": true},
   {"value": 693137, "isPrime": true},
   {"value": 693149, "isPrime": true},
   {"value": 693157, "isPrime": true},
   {"value": 693167, "isPrime": true},
   {"value": 693169, "isPrime": true},
   {"value": 693179, "isPrime": true},
   {"value": 693223, "isPrime": true},
   {"value": 693257, "isPrime": true},
   {"value": 693283, "isPrime": true},
   {"value": 693317, "isPrime": true},
   {"value": 693323, "isPrime": true},
   {"value": 693337, "isPrime": true},
   {"value": 693353, "isPrime": true},
   {"value": 693359, "isPrime": true},
   {"value": 693373, "isPrime": true},
   {"value": 693397, "isPrime": true},
   {"value": 693401, "isPrime": true},
   {"value": 693403, "isPrime": true},
   {"value": 693409, "isPrime": true},
   {"value": 693421, "isPrime": true},
   {"value": 693431, "isPrime": true},
   {"value": 693437, "isPrime": true},
   {"value": 693487, "isPrime": true},
   {"value": 693493, "isPrime": true},
   {"value": 693503, "isPrime": true},
   {"value": 693523, "isPrime": true},
   {"value": 693527, "isPrime": true},
   {"value": 693529, "isPrime": true},
   {"value": 693533, "isPrime": true},
   {"value": 693569, "isPrime": true},
   {"value": 693571, "isPrime": true},
   {"value": 693601, "isPrime": true},
   {"value": 693607, "isPrime": true},
   {"value": 693619, "isPrime": true},
   {"value": 693629, "isPrime": true},
   {"value": 693659, "isPrime": true},
   {"value": 693661, "isPrime": true},
   {"value": 693677, "isPrime": true},
   {"value": 693683, "isPrime": true},
   {"value": 693689, "isPrime": true},
   {"value": 693691, "isPrime": true},
   {"value": 693697, "isPrime": true},
   {"value": 693701, "isPrime": true},
   {"value": 693727, "isPrime": true},
   {"value": 693731, "isPrime": true},
   {"value": 693733, "isPrime": true},
   {"value": 693739, "isPrime": true},
   {"value": 693743, "isPrime": true},
   {"value": 693757, "isPrime": true},
   {"value": 693779, "isPrime": true},
   {"value": 693793, "isPrime": true},
   {"value": 693799, "isPrime": true},
   {"value": 693809, "isPrime": true},
   {"value": 693827, "isPrime": true},
   {"value": 693829, "isPrime": true},
   {"value": 693851, "isPrime": true},
   {"value": 693859, "isPrime": true},
   {"value": 693871, "isPrime": true},
   {"value": 693877, "isPrime": true},
   {"value": 693881, "isPrime": true},
   {"value": 693943, "isPrime": true},
   {"value": 693961, "isPrime": true},
   {"value": 693967, "isPrime": true},
   {"value": 693989, "isPrime": true}
]
