[
   {"value": 723029, "isPrime": true}
   {"value": 723031, "isPrime": true}
   {"value": 723043, "isPrime": true}
   {"value": 723049, "isPrime": true}
   {"value": 723053, "isPrime": true}
   {"value": 723067, "isPrime": true}
   {"value": 723071, "isPrime": true}
   {"value": 723089, "isPrime": true}
   {"value": 723101, "isPrime": true}
   {"value": 723103, "isPrime": true}
   {"value": 723109, "isPrime": true}
   {"value": 723113, "isPrime": true}
   {"value": 723119, "isPrime": true}
   {"value": 723127, "isPrime": true}
   {"value": 723133, "isPrime": true}
   {"value": 723157, "isPrime": true}
   {"value": 723161, "isPrime": true}
   {"value": 723167, "isPrime": true}
   {"value": 723169, "isPrime": true}
   {"value": 723181, "isPrime": true}
   {"value": 723193, "isPrime": true}
   {"value": 723209, "isPrime": true}
   {"value": 723221, "isPrime": true}
   {"value": 723227, "isPrime": true}
   {"value": 723257, "isPrime": true}
   {"value": 723259, "isPrime": true}
   {"value": 723263, "isPrime": true}
   {"value": 723269, "isPrime": true}
   {"value": 723271, "isPrime": true}
   {"value": 723287, "isPrime": true}
   {"value": 723293, "isPrime": true}
   {"value": 723319, "isPrime": true}
   {"value": 723337, "isPrime": true}
   {"value": 723353, "isPrime": true}
   {"value": 723361, "isPrime": true}
   {"value": 723379, "isPrime": true}
   {"value": 723391, "isPrime": true}
   {"value": 723407, "isPrime": true}
   {"value": 723409, "isPrime": true}
   {"value": 723413, "isPrime": true}
   {"value": 723421, "isPrime": true}
   {"value": 723439, "isPrime": true}
   {"value": 723451, "isPrime": true}
   {"value": 723467, "isPrime": true}
   {"value": 723473, "isPrime": true}
   {"value": 723479, "isPrime": true}
   {"value": 723491, "isPrime": true}
   {"value": 723493, "isPrime": true}
   {"value": 723529, "isPrime": true}
   {"value": 723551, "isPrime": true}
   {"value": 723553, "isPrime": true}
   {"value": 723559, "isPrime": true}
   {"value": 723563, "isPrime": true}
   {"value": 723587, "isPrime": true}
   {"value": 723589, "isPrime": true}
   {"value": 723601, "isPrime": true}
   {"value": 723607, "isPrime": true}
   {"value": 723617, "isPrime": true}
   {"value": 723623, "isPrime": true}
   {"value": 723661, "isPrime": true}
   {"value": 723721, "isPrime": true}
   {"value": 723727, "isPrime": true}
   {"value": 723739, "isPrime": true}
   {"value": 723761, "isPrime": true}
   {"value": 723791, "isPrime": true}
   {"value": 723797, "isPrime": true}
   {"value": 723799, "isPrime": true}
   {"value": 723803, "isPrime": true}
   {"value": 723823, "isPrime": true}
   {"value": 723829, "isPrime": true}
   {"value": 723839, "isPrime": true}
   {"value": 723851, "isPrime": true}
   {"value": 723857, "isPrime": true}
   {"value": 723859, "isPrime": true}
   {"value": 723893, "isPrime": true}
   {"value": 723901, "isPrime": true}
   {"value": 723907, "isPrime": true}
   {"value": 723913, "isPrime": true}
   {"value": 723917, "isPrime": true}
   {"value": 723923, "isPrime": true}
   {"value": 723949, "isPrime": true}
   {"value": 723959, "isPrime": true}
   {"value": 723967, "isPrime": true}
   {"value": 723973, "isPrime": true}
   {"value": 723977, "isPrime": true}
   {"value": 723997, "isPrime": true}
]
