[
   {"value": 760007, "isPrime": true},
   {"value": 760043, "isPrime": true},
   {"value": 760063, "isPrime": true},
   {"value": 760079, "isPrime": true},
   {"value": 760093, "isPrime": true},
   {"value": 760103, "isPrime": true},
   {"value": 760117, "isPrime": true},
   {"value": 760129, "isPrime": true},
   {"value": 760141, "isPrime": true},
   {"value": 760147, "isPrime": true},
   {"value": 760153, "isPrime": true},
   {"value": 760163, "isPrime": true},
   {"value": 760169, "isPrime": true},
   {"value": 760183, "isPrime": true},
   {"value": 760187, "isPrime": true},
   {"value": 760211, "isPrime": true},
   {"value": 760229, "isPrime": true},
   {"value": 760231, "isPrime": true},
   {"value": 760237, "isPrime": true},
   {"value": 760241, "isPrime": true},
   {"value": 760261, "isPrime": true},
   {"value": 760267, "isPrime": true},
   {"value": 760273, "isPrime": true},
   {"value": 760289, "isPrime": true},
   {"value": 760297, "isPrime": true},
   {"value": 760301, "isPrime": true},
   {"value": 760321, "isPrime": true},
   {"value": 760343, "isPrime": true},
   {"value": 760367, "isPrime": true},
   {"value": 760373, "isPrime": true},
   {"value": 760411, "isPrime": true},
   {"value": 760423, "isPrime": true},
   {"value": 760433, "isPrime": true},
   {"value": 760447, "isPrime": true},
   {"value": 760453, "isPrime": true},
   {"value": 760457, "isPrime": true},
   {"value": 760477, "isPrime": true},
   {"value": 760489, "isPrime": true},
   {"value": 760499, "isPrime": true},
   {"value": 760511, "isPrime": true},
   {"value": 760519, "isPrime": true},
   {"value": 760531, "isPrime": true},
   {"value": 760537, "isPrime": true},
   {"value": 760549, "isPrime": true},
   {"value": 760553, "isPrime": true},
   {"value": 760561, "isPrime": true},
   {"value": 760567, "isPrime": true},
   {"value": 760579, "isPrime": true},
   {"value": 760607, "isPrime": true},
   {"value": 760619, "isPrime": true},
   {"value": 760621, "isPrime": true},
   {"value": 760637, "isPrime": true},
   {"value": 760649, "isPrime": true},
   {"value": 760657, "isPrime": true},
   {"value": 760693, "isPrime": true},
   {"value": 760723, "isPrime": true},
   {"value": 760729, "isPrime": true},
   {"value": 760759, "isPrime": true},
   {"value": 760769, "isPrime": true},
   {"value": 760783, "isPrime": true},
   {"value": 760807, "isPrime": true},
   {"value": 760813, "isPrime": true},
   {"value": 760841, "isPrime": true},
   {"value": 760843, "isPrime": true},
   {"value": 760847, "isPrime": true},
   {"value": 760871, "isPrime": true},
   {"value": 760891, "isPrime": true},
   {"value": 760897, "isPrime": true},
   {"value": 760901, "isPrime": true},
   {"value": 760913, "isPrime": true},
   {"value": 760927, "isPrime": true},
   {"value": 760933, "isPrime": true},
   {"value": 760939, "isPrime": true},
   {"value": 760951, "isPrime": true},
   {"value": 760961, "isPrime": true},
   {"value": 760993, "isPrime": true},
   {"value": 760997, "isPrime": true}
]
