[
   {"value": 2570011, "isPrime": true},
   {"value": 2570017, "isPrime": true},
   {"value": 2570047, "isPrime": true},
   {"value": 2570069, "isPrime": true},
   {"value": 2570083, "isPrime": true},
   {"value": 2570119, "isPrime": true},
   {"value": 2570137, "isPrime": true},
   {"value": 2570177, "isPrime": true},
   {"value": 2570189, "isPrime": true},
   {"value": 2570201, "isPrime": true},
   {"value": 2570203, "isPrime": true},
   {"value": 2570207, "isPrime": true},
   {"value": 2570219, "isPrime": true},
   {"value": 2570221, "isPrime": true},
   {"value": 2570233, "isPrime": true},
   {"value": 2570251, "isPrime": true},
   {"value": 2570311, "isPrime": true},
   {"value": 2570317, "isPrime": true},
   {"value": 2570327, "isPrime": true},
   {"value": 2570333, "isPrime": true},
   {"value": 2570363, "isPrime": true},
   {"value": 2570369, "isPrime": true},
   {"value": 2570371, "isPrime": true},
   {"value": 2570387, "isPrime": true},
   {"value": 2570389, "isPrime": true},
   {"value": 2570401, "isPrime": true},
   {"value": 2570419, "isPrime": true},
   {"value": 2570429, "isPrime": true},
   {"value": 2570431, "isPrime": true},
   {"value": 2570437, "isPrime": true},
   {"value": 2570441, "isPrime": true},
   {"value": 2570459, "isPrime": true},
   {"value": 2570467, "isPrime": true},
   {"value": 2570471, "isPrime": true},
   {"value": 2570507, "isPrime": true},
   {"value": 2570509, "isPrime": true},
   {"value": 2570537, "isPrime": true},
   {"value": 2570539, "isPrime": true},
   {"value": 2570563, "isPrime": true},
   {"value": 2570573, "isPrime": true},
   {"value": 2570591, "isPrime": true},
   {"value": 2570599, "isPrime": true},
   {"value": 2570609, "isPrime": true},
   {"value": 2570611, "isPrime": true},
   {"value": 2570627, "isPrime": true},
   {"value": 2570639, "isPrime": true},
   {"value": 2570651, "isPrime": true},
   {"value": 2570657, "isPrime": true},
   {"value": 2570663, "isPrime": true},
   {"value": 2570671, "isPrime": true},
   {"value": 2570677, "isPrime": true},
   {"value": 2570683, "isPrime": true},
   {"value": 2570693, "isPrime": true},
   {"value": 2570699, "isPrime": true},
   {"value": 2570713, "isPrime": true},
   {"value": 2570717, "isPrime": true},
   {"value": 2570749, "isPrime": true},
   {"value": 2570761, "isPrime": true},
   {"value": 2570773, "isPrime": true},
   {"value": 2570783, "isPrime": true},
   {"value": 2570801, "isPrime": true},
   {"value": 2570809, "isPrime": true},
   {"value": 2570831, "isPrime": true},
   {"value": 2570849, "isPrime": true},
   {"value": 2570851, "isPrime": true},
   {"value": 2570891, "isPrime": true},
   {"value": 2570903, "isPrime": true},
   {"value": 2570921, "isPrime": true},
   {"value": 2570933, "isPrime": true},
   {"value": 2570941, "isPrime": true},
   {"value": 2570951, "isPrime": true},
   {"value": 2570957, "isPrime": true},
   {"value": 2570969, "isPrime": true},
   {"value": 2570989, "isPrime": true}
]
