[
   {"value": 12246029, "isPrime": true},
   {"value": 12246037, "isPrime": true},
   {"value": 12246053, "isPrime": true},
   {"value": 12246067, "isPrime": true},
   {"value": 12246071, "isPrime": true},
   {"value": 12246077, "isPrime": true},
   {"value": 12246119, "isPrime": true},
   {"value": 12246131, "isPrime": true},
   {"value": 12246163, "isPrime": true},
   {"value": 12246181, "isPrime": true},
   {"value": 12246187, "isPrime": true},
   {"value": 12246191, "isPrime": true},
   {"value": 12246211, "isPrime": true},
   {"value": 12246287, "isPrime": true},
   {"value": 12246301, "isPrime": true},
   {"value": 12246319, "isPrime": true},
   {"value": 12246329, "isPrime": true},
   {"value": 12246337, "isPrime": true},
   {"value": 12246349, "isPrime": true},
   {"value": 12246361, "isPrime": true},
   {"value": 12246379, "isPrime": true},
   {"value": 12246383, "isPrime": true},
   {"value": 12246433, "isPrime": true},
   {"value": 12246449, "isPrime": true},
   {"value": 12246463, "isPrime": true},
   {"value": 12246467, "isPrime": true},
   {"value": 12246473, "isPrime": true},
   {"value": 12246503, "isPrime": true},
   {"value": 12246523, "isPrime": true},
   {"value": 12246527, "isPrime": true},
   {"value": 12246547, "isPrime": true},
   {"value": 12246569, "isPrime": true},
   {"value": 12246607, "isPrime": true},
   {"value": 12246623, "isPrime": true},
   {"value": 12246631, "isPrime": true},
   {"value": 12246653, "isPrime": true},
   {"value": 12246677, "isPrime": true},
   {"value": 12246683, "isPrime": true},
   {"value": 12246721, "isPrime": true},
   {"value": 12246769, "isPrime": true},
   {"value": 12246779, "isPrime": true},
   {"value": 12246799, "isPrime": true},
   {"value": 12246847, "isPrime": true},
   {"value": 12246853, "isPrime": true},
   {"value": 12246859, "isPrime": true},
   {"value": 12246881, "isPrime": true},
   {"value": 12246893, "isPrime": true},
   {"value": 12246901, "isPrime": true},
   {"value": 12246907, "isPrime": true},
   {"value": 12246943, "isPrime": true},
   {"value": 12246967, "isPrime": true},
   {"value": 12246973, "isPrime": true},
   {"value": 12246977, "isPrime": true},
   {"value": 12246979, "isPrime": true},
   {"value": 12246989, "isPrime": true}
]
