[
   {"value": 12368009, "isPrime": true},
   {"value": 12368017, "isPrime": true},
   {"value": 12368021, "isPrime": true},
   {"value": 12368029, "isPrime": true},
   {"value": 12368051, "isPrime": true},
   {"value": 12368053, "isPrime": true},
   {"value": 12368071, "isPrime": true},
   {"value": 12368087, "isPrime": true},
   {"value": 12368093, "isPrime": true},
   {"value": 12368099, "isPrime": true},
   {"value": 12368131, "isPrime": true},
   {"value": 12368143, "isPrime": true},
   {"value": 12368173, "isPrime": true},
   {"value": 12368203, "isPrime": true},
   {"value": 12368207, "isPrime": true},
   {"value": 12368233, "isPrime": true},
   {"value": 12368243, "isPrime": true},
   {"value": 12368269, "isPrime": true},
   {"value": 12368281, "isPrime": true},
   {"value": 12368309, "isPrime": true},
   {"value": 12368311, "isPrime": true},
   {"value": 12368329, "isPrime": true},
   {"value": 12368357, "isPrime": true},
   {"value": 12368381, "isPrime": true},
   {"value": 12368387, "isPrime": true},
   {"value": 12368393, "isPrime": true},
   {"value": 12368399, "isPrime": true},
   {"value": 12368417, "isPrime": true},
   {"value": 12368423, "isPrime": true},
   {"value": 12368437, "isPrime": true},
   {"value": 12368441, "isPrime": true},
   {"value": 12368443, "isPrime": true},
   {"value": 12368453, "isPrime": true},
   {"value": 12368459, "isPrime": true},
   {"value": 12368467, "isPrime": true},
   {"value": 12368479, "isPrime": true},
   {"value": 12368491, "isPrime": true},
   {"value": 12368507, "isPrime": true},
   {"value": 12368509, "isPrime": true},
   {"value": 12368513, "isPrime": true},
   {"value": 12368539, "isPrime": true},
   {"value": 12368579, "isPrime": true},
   {"value": 12368581, "isPrime": true},
   {"value": 12368591, "isPrime": true},
   {"value": 12368599, "isPrime": true},
   {"value": 12368621, "isPrime": true},
   {"value": 12368633, "isPrime": true},
   {"value": 12368651, "isPrime": true},
   {"value": 12368683, "isPrime": true},
   {"value": 12368689, "isPrime": true},
   {"value": 12368717, "isPrime": true},
   {"value": 12368729, "isPrime": true},
   {"value": 12368789, "isPrime": true},
   {"value": 12368813, "isPrime": true},
   {"value": 12368831, "isPrime": true},
   {"value": 12368833, "isPrime": true},
   {"value": 12368857, "isPrime": true},
   {"value": 12368861, "isPrime": true},
   {"value": 12368869, "isPrime": true},
   {"value": 12368887, "isPrime": true},
   {"value": 12368891, "isPrime": true},
   {"value": 12368893, "isPrime": true},
   {"value": 12368899, "isPrime": true},
   {"value": 12368903, "isPrime": true},
   {"value": 12368927, "isPrime": true},
   {"value": 12368933, "isPrime": true},
   {"value": 12368947, "isPrime": true},
   {"value": 12368971, "isPrime": true}
]
