[
   {"value": 5120029, "isPrime": true}
   {"value": 5120033, "isPrime": true}
   {"value": 5120047, "isPrime": true}
   {"value": 5120051, "isPrime": true}
   {"value": 5120113, "isPrime": true}
   {"value": 5120117, "isPrime": true}
   {"value": 5120119, "isPrime": true}
   {"value": 5120123, "isPrime": true}
   {"value": 5120131, "isPrime": true}
   {"value": 5120183, "isPrime": true}
   {"value": 5120189, "isPrime": true}
   {"value": 5120201, "isPrime": true}
   {"value": 5120221, "isPrime": true}
   {"value": 5120231, "isPrime": true}
   {"value": 5120249, "isPrime": true}
   {"value": 5120251, "isPrime": true}
   {"value": 5120257, "isPrime": true}
   {"value": 5120263, "isPrime": true}
   {"value": 5120267, "isPrime": true}
   {"value": 5120273, "isPrime": true}
   {"value": 5120287, "isPrime": true}
   {"value": 5120299, "isPrime": true}
   {"value": 5120333, "isPrime": true}
   {"value": 5120351, "isPrime": true}
   {"value": 5120359, "isPrime": true}
   {"value": 5120371, "isPrime": true}
   {"value": 5120399, "isPrime": true}
   {"value": 5120411, "isPrime": true}
   {"value": 5120413, "isPrime": true}
   {"value": 5120419, "isPrime": true}
   {"value": 5120441, "isPrime": true}
   {"value": 5120459, "isPrime": true}
   {"value": 5120461, "isPrime": true}
   {"value": 5120477, "isPrime": true}
   {"value": 5120491, "isPrime": true}
   {"value": 5120503, "isPrime": true}
   {"value": 5120537, "isPrime": true}
   {"value": 5120539, "isPrime": true}
   {"value": 5120567, "isPrime": true}
   {"value": 5120573, "isPrime": true}
   {"value": 5120597, "isPrime": true}
   {"value": 5120629, "isPrime": true}
   {"value": 5120657, "isPrime": true}
   {"value": 5120677, "isPrime": true}
   {"value": 5120681, "isPrime": true}
   {"value": 5120707, "isPrime": true}
   {"value": 5120719, "isPrime": true}
   {"value": 5120729, "isPrime": true}
   {"value": 5120737, "isPrime": true}
   {"value": 5120809, "isPrime": true}
   {"value": 5120813, "isPrime": true}
   {"value": 5120831, "isPrime": true}
   {"value": 5120833, "isPrime": true}
   {"value": 5120839, "isPrime": true}
   {"value": 5120879, "isPrime": true}
   {"value": 5120887, "isPrime": true}
   {"value": 5120891, "isPrime": true}
   {"value": 5120939, "isPrime": true}
   {"value": 5120957, "isPrime": true}
   {"value": 5120959, "isPrime": true}
   {"value": 5120963, "isPrime": true}
]
