[
   {"value": 5980021, "isPrime": true}
   {"value": 5980031, "isPrime": true}
   {"value": 5980033, "isPrime": true}
   {"value": 5980081, "isPrime": true}
   {"value": 5980099, "isPrime": true}
   {"value": 5980111, "isPrime": true}
   {"value": 5980127, "isPrime": true}
   {"value": 5980129, "isPrime": true}
   {"value": 5980151, "isPrime": true}
   {"value": 5980171, "isPrime": true}
   {"value": 5980189, "isPrime": true}
   {"value": 5980201, "isPrime": true}
   {"value": 5980223, "isPrime": true}
   {"value": 5980229, "isPrime": true}
   {"value": 5980237, "isPrime": true}
   {"value": 5980267, "isPrime": true}
   {"value": 5980279, "isPrime": true}
   {"value": 5980291, "isPrime": true}
   {"value": 5980319, "isPrime": true}
   {"value": 5980321, "isPrime": true}
   {"value": 5980333, "isPrime": true}
   {"value": 5980339, "isPrime": true}
   {"value": 5980363, "isPrime": true}
   {"value": 5980367, "isPrime": true}
   {"value": 5980393, "isPrime": true}
   {"value": 5980433, "isPrime": true}
   {"value": 5980439, "isPrime": true}
   {"value": 5980453, "isPrime": true}
   {"value": 5980477, "isPrime": true}
   {"value": 5980493, "isPrime": true}
   {"value": 5980517, "isPrime": true}
   {"value": 5980519, "isPrime": true}
   {"value": 5980531, "isPrime": true}
   {"value": 5980561, "isPrime": true}
   {"value": 5980567, "isPrime": true}
   {"value": 5980589, "isPrime": true}
   {"value": 5980591, "isPrime": true}
   {"value": 5980607, "isPrime": true}
   {"value": 5980619, "isPrime": true}
   {"value": 5980631, "isPrime": true}
   {"value": 5980661, "isPrime": true}
   {"value": 5980669, "isPrime": true}
   {"value": 5980673, "isPrime": true}
   {"value": 5980691, "isPrime": true}
   {"value": 5980693, "isPrime": true}
   {"value": 5980747, "isPrime": true}
   {"value": 5980781, "isPrime": true}
   {"value": 5980829, "isPrime": true}
   {"value": 5980859, "isPrime": true}
   {"value": 5980903, "isPrime": true}
   {"value": 5980921, "isPrime": true}
   {"value": 5980967, "isPrime": true}
   {"value": 5980973, "isPrime": true}
   {"value": 5980981, "isPrime": true}
]
