[
   {"value": 3490021, "isPrime": true},
   {"value": 3490031, "isPrime": true},
   {"value": 3490033, "isPrime": true},
   {"value": 3490051, "isPrime": true},
   {"value": 3490127, "isPrime": true},
   {"value": 3490139, "isPrime": true},
   {"value": 3490153, "isPrime": true},
   {"value": 3490159, "isPrime": true},
   {"value": 3490171, "isPrime": true},
   {"value": 3490177, "isPrime": true},
   {"value": 3490183, "isPrime": true},
   {"value": 3490187, "isPrime": true},
   {"value": 3490199, "isPrime": true},
   {"value": 3490217, "isPrime": true},
   {"value": 3490229, "isPrime": true},
   {"value": 3490271, "isPrime": true},
   {"value": 3490303, "isPrime": true},
   {"value": 3490307, "isPrime": true},
   {"value": 3490337, "isPrime": true},
   {"value": 3490363, "isPrime": true},
   {"value": 3490367, "isPrime": true},
   {"value": 3490379, "isPrime": true},
   {"value": 3490387, "isPrime": true},
   {"value": 3490393, "isPrime": true},
   {"value": 3490427, "isPrime": true},
   {"value": 3490441, "isPrime": true},
   {"value": 3490451, "isPrime": true},
   {"value": 3490463, "isPrime": true},
   {"value": 3490483, "isPrime": true},
   {"value": 3490493, "isPrime": true},
   {"value": 3490517, "isPrime": true},
   {"value": 3490577, "isPrime": true},
   {"value": 3490589, "isPrime": true},
   {"value": 3490607, "isPrime": true},
   {"value": 3490609, "isPrime": true},
   {"value": 3490639, "isPrime": true},
   {"value": 3490649, "isPrime": true},
   {"value": 3490651, "isPrime": true},
   {"value": 3490673, "isPrime": true},
   {"value": 3490681, "isPrime": true},
   {"value": 3490703, "isPrime": true},
   {"value": 3490709, "isPrime": true},
   {"value": 3490727, "isPrime": true},
   {"value": 3490769, "isPrime": true},
   {"value": 3490771, "isPrime": true},
   {"value": 3490777, "isPrime": true},
   {"value": 3490789, "isPrime": true},
   {"value": 3490793, "isPrime": true},
   {"value": 3490807, "isPrime": true},
   {"value": 3490811, "isPrime": true},
   {"value": 3490819, "isPrime": true},
   {"value": 3490829, "isPrime": true},
   {"value": 3490841, "isPrime": true},
   {"value": 3490843, "isPrime": true},
   {"value": 3490859, "isPrime": true},
   {"value": 3490867, "isPrime": true},
   {"value": 3490873, "isPrime": true},
   {"value": 3490891, "isPrime": true},
   {"value": 3490937, "isPrime": true},
   {"value": 3490939, "isPrime": true},
   {"value": 3490957, "isPrime": true},
   {"value": 3490961, "isPrime": true},
   {"value": 3490973, "isPrime": true}
]
