[
   {"value": 3633001, "isPrime": true},
   {"value": 3633013, "isPrime": true},
   {"value": 3633017, "isPrime": true},
   {"value": 3633029, "isPrime": true},
   {"value": 3633037, "isPrime": true},
   {"value": 3633041, "isPrime": true},
   {"value": 3633059, "isPrime": true},
   {"value": 3633073, "isPrime": true},
   {"value": 3633083, "isPrime": true},
   {"value": 3633101, "isPrime": true},
   {"value": 3633109, "isPrime": true},
   {"value": 3633127, "isPrime": true},
   {"value": 3633139, "isPrime": true},
   {"value": 3633151, "isPrime": true},
   {"value": 3633167, "isPrime": true},
   {"value": 3633181, "isPrime": true},
   {"value": 3633187, "isPrime": true},
   {"value": 3633191, "isPrime": true},
   {"value": 3633193, "isPrime": true},
   {"value": 3633229, "isPrime": true},
   {"value": 3633233, "isPrime": true},
   {"value": 3633263, "isPrime": true},
   {"value": 3633269, "isPrime": true},
   {"value": 3633299, "isPrime": true},
   {"value": 3633317, "isPrime": true},
   {"value": 3633337, "isPrime": true},
   {"value": 3633347, "isPrime": true},
   {"value": 3633349, "isPrime": true},
   {"value": 3633353, "isPrime": true},
   {"value": 3633361, "isPrime": true},
   {"value": 3633367, "isPrime": true},
   {"value": 3633373, "isPrime": true},
   {"value": 3633391, "isPrime": true},
   {"value": 3633401, "isPrime": true},
   {"value": 3633403, "isPrime": true},
   {"value": 3633431, "isPrime": true},
   {"value": 3633449, "isPrime": true},
   {"value": 3633499, "isPrime": true},
   {"value": 3633551, "isPrime": true},
   {"value": 3633559, "isPrime": true},
   {"value": 3633569, "isPrime": true},
   {"value": 3633571, "isPrime": true},
   {"value": 3633577, "isPrime": true},
   {"value": 3633583, "isPrime": true},
   {"value": 3633647, "isPrime": true},
   {"value": 3633653, "isPrime": true},
   {"value": 3633661, "isPrime": true},
   {"value": 3633673, "isPrime": true},
   {"value": 3633683, "isPrime": true},
   {"value": 3633689, "isPrime": true},
   {"value": 3633697, "isPrime": true},
   {"value": 3633703, "isPrime": true},
   {"value": 3633713, "isPrime": true},
   {"value": 3633719, "isPrime": true},
   {"value": 3633743, "isPrime": true},
   {"value": 3633779, "isPrime": true},
   {"value": 3633797, "isPrime": true},
   {"value": 3633803, "isPrime": true},
   {"value": 3633821, "isPrime": true},
   {"value": 3633853, "isPrime": true},
   {"value": 3633857, "isPrime": true},
   {"value": 3633859, "isPrime": true},
   {"value": 3633863, "isPrime": true},
   {"value": 3633893, "isPrime": true},
   {"value": 3633901, "isPrime": true},
   {"value": 3633907, "isPrime": true},
   {"value": 3633919, "isPrime": true},
   {"value": 3633923, "isPrime": true},
   {"value": 3633941, "isPrime": true},
   {"value": 3633983, "isPrime": true},
   {"value": 3633991, "isPrime": true}
]
