[
   {"value": 3790001, "isPrime": true}
   {"value": 3790057, "isPrime": true}
   {"value": 3790067, "isPrime": true}
   {"value": 3790069, "isPrime": true}
   {"value": 3790103, "isPrime": true}
   {"value": 3790121, "isPrime": true}
   {"value": 3790187, "isPrime": true}
   {"value": 3790229, "isPrime": true}
   {"value": 3790247, "isPrime": true}
   {"value": 3790273, "isPrime": true}
   {"value": 3790279, "isPrime": true}
   {"value": 3790289, "isPrime": true}
   {"value": 3790309, "isPrime": true}
   {"value": 3790333, "isPrime": true}
   {"value": 3790349, "isPrime": true}
   {"value": 3790373, "isPrime": true}
   {"value": 3790393, "isPrime": true}
   {"value": 3790433, "isPrime": true}
   {"value": 3790441, "isPrime": true}
   {"value": 3790447, "isPrime": true}
   {"value": 3790453, "isPrime": true}
   {"value": 3790459, "isPrime": true}
   {"value": 3790471, "isPrime": true}
   {"value": 3790483, "isPrime": true}
   {"value": 3790487, "isPrime": true}
   {"value": 3790513, "isPrime": true}
   {"value": 3790517, "isPrime": true}
   {"value": 3790531, "isPrime": true}
   {"value": 3790537, "isPrime": true}
   {"value": 3790543, "isPrime": true}
   {"value": 3790547, "isPrime": true}
   {"value": 3790559, "isPrime": true}
   {"value": 3790571, "isPrime": true}
   {"value": 3790583, "isPrime": true}
   {"value": 3790621, "isPrime": true}
   {"value": 3790651, "isPrime": true}
   {"value": 3790667, "isPrime": true}
   {"value": 3790697, "isPrime": true}
   {"value": 3790729, "isPrime": true}
   {"value": 3790739, "isPrime": true}
   {"value": 3790741, "isPrime": true}
   {"value": 3790753, "isPrime": true}
   {"value": 3790757, "isPrime": true}
   {"value": 3790763, "isPrime": true}
   {"value": 3790769, "isPrime": true}
   {"value": 3790771, "isPrime": true}
   {"value": 3790781, "isPrime": true}
   {"value": 3790783, "isPrime": true}
   {"value": 3790789, "isPrime": true}
   {"value": 3790807, "isPrime": true}
   {"value": 3790889, "isPrime": true}
   {"value": 3790921, "isPrime": true}
   {"value": 3790933, "isPrime": true}
   {"value": 3790939, "isPrime": true}
   {"value": 3790951, "isPrime": true}
   {"value": 3790961, "isPrime": true}
   {"value": 3790981, "isPrime": true}
   {"value": 3790991, "isPrime": true}
   {"value": 3790993, "isPrime": true}
   {"value": 3790999, "isPrime": true}
]
