[
   {"value": 6221003, "isPrime": true},
   {"value": 6221009, "isPrime": true},
   {"value": 6221023, "isPrime": true},
   {"value": 6221027, "isPrime": true},
   {"value": 6221041, "isPrime": true},
   {"value": 6221071, "isPrime": true},
   {"value": 6221077, "isPrime": true},
   {"value": 6221081, "isPrime": true},
   {"value": 6221093, "isPrime": true},
   {"value": 6221101, "isPrime": true},
   {"value": 6221107, "isPrime": true},
   {"value": 6221119, "isPrime": true},
   {"value": 6221123, "isPrime": true},
   {"value": 6221147, "isPrime": true},
   {"value": 6221153, "isPrime": true},
   {"value": 6221161, "isPrime": true},
   {"value": 6221177, "isPrime": true},
   {"value": 6221179, "isPrime": true},
   {"value": 6221183, "isPrime": true},
   {"value": 6221191, "isPrime": true},
   {"value": 6221203, "isPrime": true},
   {"value": 6221209, "isPrime": true},
   {"value": 6221213, "isPrime": true},
   {"value": 6221231, "isPrime": true},
   {"value": 6221239, "isPrime": true},
   {"value": 6221263, "isPrime": true},
   {"value": 6221273, "isPrime": true},
   {"value": 6221287, "isPrime": true},
   {"value": 6221309, "isPrime": true},
   {"value": 6221311, "isPrime": true},
   {"value": 6221317, "isPrime": true},
   {"value": 6221377, "isPrime": true},
   {"value": 6221429, "isPrime": true},
   {"value": 6221459, "isPrime": true},
   {"value": 6221471, "isPrime": true},
   {"value": 6221489, "isPrime": true},
   {"value": 6221497, "isPrime": true},
   {"value": 6221539, "isPrime": true},
   {"value": 6221543, "isPrime": true},
   {"value": 6221549, "isPrime": true},
   {"value": 6221557, "isPrime": true},
   {"value": 6221561, "isPrime": true},
   {"value": 6221563, "isPrime": true},
   {"value": 6221591, "isPrime": true},
   {"value": 6221629, "isPrime": true},
   {"value": 6221639, "isPrime": true},
   {"value": 6221647, "isPrime": true},
   {"value": 6221651, "isPrime": true},
   {"value": 6221671, "isPrime": true},
   {"value": 6221693, "isPrime": true},
   {"value": 6221749, "isPrime": true},
   {"value": 6221767, "isPrime": true},
   {"value": 6221771, "isPrime": true},
   {"value": 6221773, "isPrime": true},
   {"value": 6221819, "isPrime": true},
   {"value": 6221827, "isPrime": true},
   {"value": 6221833, "isPrime": true},
   {"value": 6221837, "isPrime": true},
   {"value": 6221849, "isPrime": true},
   {"value": 6221867, "isPrime": true},
   {"value": 6221869, "isPrime": true},
   {"value": 6221879, "isPrime": true},
   {"value": 6221909, "isPrime": true},
   {"value": 6221927, "isPrime": true},
   {"value": 6221933, "isPrime": true},
   {"value": 6221951, "isPrime": true},
   {"value": 6221953, "isPrime": true},
   {"value": 6221977, "isPrime": true},
   {"value": 6221981, "isPrime": true},
   {"value": 6221989, "isPrime": true}
]
