[
   {"value": 10023001, "isPrime": true}
   {"value": 10023007, "isPrime": true}
   {"value": 10023023, "isPrime": true}
   {"value": 10023031, "isPrime": true}
   {"value": 10023049, "isPrime": true}
   {"value": 10023053, "isPrime": true}
   {"value": 10023061, "isPrime": true}
   {"value": 10023071, "isPrime": true}
   {"value": 10023073, "isPrime": true}
   {"value": 10023077, "isPrime": true}
   {"value": 10023103, "isPrime": true}
   {"value": 10023109, "isPrime": true}
   {"value": 10023113, "isPrime": true}
   {"value": 10023161, "isPrime": true}
   {"value": 10023179, "isPrime": true}
   {"value": 10023187, "isPrime": true}
   {"value": 10023191, "isPrime": true}
   {"value": 10023197, "isPrime": true}
   {"value": 10023253, "isPrime": true}
   {"value": 10023259, "isPrime": true}
   {"value": 10023271, "isPrime": true}
   {"value": 10023287, "isPrime": true}
   {"value": 10023347, "isPrime": true}
   {"value": 10023367, "isPrime": true}
   {"value": 10023371, "isPrime": true}
   {"value": 10023389, "isPrime": true}
   {"value": 10023397, "isPrime": true}
   {"value": 10023407, "isPrime": true}
   {"value": 10023443, "isPrime": true}
   {"value": 10023449, "isPrime": true}
   {"value": 10023499, "isPrime": true}
   {"value": 10023511, "isPrime": true}
   {"value": 10023521, "isPrime": true}
   {"value": 10023527, "isPrime": true}
   {"value": 10023529, "isPrime": true}
   {"value": 10023539, "isPrime": true}
   {"value": 10023553, "isPrime": true}
   {"value": 10023593, "isPrime": true}
   {"value": 10023613, "isPrime": true}
   {"value": 10023623, "isPrime": true}
   {"value": 10023631, "isPrime": true}
   {"value": 10023641, "isPrime": true}
   {"value": 10023649, "isPrime": true}
   {"value": 10023667, "isPrime": true}
   {"value": 10023679, "isPrime": true}
   {"value": 10023683, "isPrime": true}
   {"value": 10023691, "isPrime": true}
   {"value": 10023701, "isPrime": true}
   {"value": 10023743, "isPrime": true}
   {"value": 10023751, "isPrime": true}
   {"value": 10023779, "isPrime": true}
   {"value": 10023787, "isPrime": true}
   {"value": 10023817, "isPrime": true}
   {"value": 10023847, "isPrime": true}
   {"value": 10023877, "isPrime": true}
   {"value": 10023889, "isPrime": true}
   {"value": 10023901, "isPrime": true}
   {"value": 10023907, "isPrime": true}
   {"value": 10023911, "isPrime": true}
   {"value": 10023917, "isPrime": true}
   {"value": 10023919, "isPrime": true}
   {"value": 10023941, "isPrime": true}
   {"value": 10023953, "isPrime": true}
   {"value": 10023991, "isPrime": true}
]
