[
   {"value": 10231009, "isPrime": true},
   {"value": 10231037, "isPrime": true},
   {"value": 10231043, "isPrime": true},
   {"value": 10231049, "isPrime": true},
   {"value": 10231051, "isPrime": true},
   {"value": 10231057, "isPrime": true},
   {"value": 10231061, "isPrime": true},
   {"value": 10231069, "isPrime": true},
   {"value": 10231073, "isPrime": true},
   {"value": 10231097, "isPrime": true},
   {"value": 10231121, "isPrime": true},
   {"value": 10231153, "isPrime": true},
   {"value": 10231163, "isPrime": true},
   {"value": 10231183, "isPrime": true},
   {"value": 10231201, "isPrime": true},
   {"value": 10231237, "isPrime": true},
   {"value": 10231241, "isPrime": true},
   {"value": 10231261, "isPrime": true},
   {"value": 10231283, "isPrime": true},
   {"value": 10231301, "isPrime": true},
   {"value": 10231303, "isPrime": true},
   {"value": 10231337, "isPrime": true},
   {"value": 10231339, "isPrime": true},
   {"value": 10231349, "isPrime": true},
   {"value": 10231379, "isPrime": true},
   {"value": 10231381, "isPrime": true},
   {"value": 10231411, "isPrime": true},
   {"value": 10231421, "isPrime": true},
   {"value": 10231439, "isPrime": true},
   {"value": 10231453, "isPrime": true},
   {"value": 10231471, "isPrime": true},
   {"value": 10231511, "isPrime": true},
   {"value": 10231531, "isPrime": true},
   {"value": 10231537, "isPrime": true},
   {"value": 10231547, "isPrime": true},
   {"value": 10231553, "isPrime": true},
   {"value": 10231567, "isPrime": true},
   {"value": 10231621, "isPrime": true},
   {"value": 10231649, "isPrime": true},
   {"value": 10231667, "isPrime": true},
   {"value": 10231687, "isPrime": true},
   {"value": 10231691, "isPrime": true},
   {"value": 10231699, "isPrime": true},
   {"value": 10231733, "isPrime": true},
   {"value": 10231777, "isPrime": true},
   {"value": 10231789, "isPrime": true},
   {"value": 10231799, "isPrime": true},
   {"value": 10231801, "isPrime": true},
   {"value": 10231813, "isPrime": true},
   {"value": 10231817, "isPrime": true},
   {"value": 10231831, "isPrime": true},
   {"value": 10231873, "isPrime": true},
   {"value": 10231877, "isPrime": true},
   {"value": 10231883, "isPrime": true},
   {"value": 10231889, "isPrime": true},
   {"value": 10231901, "isPrime": true},
   {"value": 10231913, "isPrime": true},
   {"value": 10231927, "isPrime": true},
   {"value": 10231951, "isPrime": true},
   {"value": 10231961, "isPrime": true},
   {"value": 10231973, "isPrime": true},
   {"value": 10231981, "isPrime": true},
   {"value": 10231993, "isPrime": true}
]
