[
   {"value": 10299001, "isPrime": true}
   {"value": 10299011, "isPrime": true}
   {"value": 10299019, "isPrime": true}
   {"value": 10299049, "isPrime": true}
   {"value": 10299067, "isPrime": true}
   {"value": 10299097, "isPrime": true}
   {"value": 10299103, "isPrime": true}
   {"value": 10299109, "isPrime": true}
   {"value": 10299131, "isPrime": true}
   {"value": 10299139, "isPrime": true}
   {"value": 10299143, "isPrime": true}
   {"value": 10299167, "isPrime": true}
   {"value": 10299181, "isPrime": true}
   {"value": 10299199, "isPrime": true}
   {"value": 10299259, "isPrime": true}
   {"value": 10299269, "isPrime": true}
   {"value": 10299281, "isPrime": true}
   {"value": 10299287, "isPrime": true}
   {"value": 10299313, "isPrime": true}
   {"value": 10299353, "isPrime": true}
   {"value": 10299389, "isPrime": true}
   {"value": 10299427, "isPrime": true}
   {"value": 10299449, "isPrime": true}
   {"value": 10299451, "isPrime": true}
   {"value": 10299479, "isPrime": true}
   {"value": 10299491, "isPrime": true}
   {"value": 10299503, "isPrime": true}
   {"value": 10299521, "isPrime": true}
   {"value": 10299529, "isPrime": true}
   {"value": 10299547, "isPrime": true}
   {"value": 10299551, "isPrime": true}
   {"value": 10299587, "isPrime": true}
   {"value": 10299589, "isPrime": true}
   {"value": 10299623, "isPrime": true}
   {"value": 10299659, "isPrime": true}
   {"value": 10299673, "isPrime": true}
   {"value": 10299683, "isPrime": true}
   {"value": 10299697, "isPrime": true}
   {"value": 10299743, "isPrime": true}
   {"value": 10299763, "isPrime": true}
   {"value": 10299799, "isPrime": true}
   {"value": 10299803, "isPrime": true}
   {"value": 10299811, "isPrime": true}
   {"value": 10299851, "isPrime": true}
   {"value": 10299853, "isPrime": true}
   {"value": 10299871, "isPrime": true}
   {"value": 10299889, "isPrime": true}
   {"value": 10299907, "isPrime": true}
   {"value": 10299917, "isPrime": true}
   {"value": 10299953, "isPrime": true}
   {"value": 10299973, "isPrime": true}
   {"value": 10299983, "isPrime": true}
   {"value": 10299997, "isPrime": true}
]
