[
   {"value": 10696003, "isPrime": true},
   {"value": 10696073, "isPrime": true},
   {"value": 10696097, "isPrime": true},
   {"value": 10696123, "isPrime": true},
   {"value": 10696129, "isPrime": true},
   {"value": 10696141, "isPrime": true},
   {"value": 10696163, "isPrime": true},
   {"value": 10696171, "isPrime": true},
   {"value": 10696177, "isPrime": true},
   {"value": 10696181, "isPrime": true},
   {"value": 10696193, "isPrime": true},
   {"value": 10696199, "isPrime": true},
   {"value": 10696201, "isPrime": true},
   {"value": 10696211, "isPrime": true},
   {"value": 10696249, "isPrime": true},
   {"value": 10696261, "isPrime": true},
   {"value": 10696291, "isPrime": true},
   {"value": 10696313, "isPrime": true},
   {"value": 10696319, "isPrime": true},
   {"value": 10696337, "isPrime": true},
   {"value": 10696391, "isPrime": true},
   {"value": 10696397, "isPrime": true},
   {"value": 10696421, "isPrime": true},
   {"value": 10696423, "isPrime": true},
   {"value": 10696429, "isPrime": true},
   {"value": 10696453, "isPrime": true},
   {"value": 10696489, "isPrime": true},
   {"value": 10696529, "isPrime": true},
   {"value": 10696547, "isPrime": true},
   {"value": 10696571, "isPrime": true},
   {"value": 10696579, "isPrime": true},
   {"value": 10696591, "isPrime": true},
   {"value": 10696627, "isPrime": true},
   {"value": 10696657, "isPrime": true},
   {"value": 10696661, "isPrime": true},
   {"value": 10696667, "isPrime": true},
   {"value": 10696681, "isPrime": true},
   {"value": 10696687, "isPrime": true},
   {"value": 10696709, "isPrime": true},
   {"value": 10696727, "isPrime": true},
   {"value": 10696729, "isPrime": true},
   {"value": 10696739, "isPrime": true},
   {"value": 10696747, "isPrime": true},
   {"value": 10696781, "isPrime": true},
   {"value": 10696783, "isPrime": true},
   {"value": 10696787, "isPrime": true},
   {"value": 10696799, "isPrime": true},
   {"value": 10696841, "isPrime": true},
   {"value": 10696843, "isPrime": true},
   {"value": 10696849, "isPrime": true},
   {"value": 10696883, "isPrime": true},
   {"value": 10696913, "isPrime": true},
   {"value": 10696951, "isPrime": true},
   {"value": 10696967, "isPrime": true},
   {"value": 10696993, "isPrime": true},
   {"value": 10696997, "isPrime": true}
]
