[
   {"value": 1167011, "isPrime": true}
   {"value": 1167013, "isPrime": true}
   {"value": 1167053, "isPrime": true}
   {"value": 1167059, "isPrime": true}
   {"value": 1167077, "isPrime": true}
   {"value": 1167083, "isPrime": true}
   {"value": 1167139, "isPrime": true}
   {"value": 1167143, "isPrime": true}
   {"value": 1167157, "isPrime": true}
   {"value": 1167167, "isPrime": true}
   {"value": 1167193, "isPrime": true}
   {"value": 1167209, "isPrime": true}
   {"value": 1167211, "isPrime": true}
   {"value": 1167217, "isPrime": true}
   {"value": 1167233, "isPrime": true}
   {"value": 1167241, "isPrime": true}
   {"value": 1167251, "isPrime": true}
   {"value": 1167277, "isPrime": true}
   {"value": 1167289, "isPrime": true}
   {"value": 1167293, "isPrime": true}
   {"value": 1167307, "isPrime": true}
   {"value": 1167317, "isPrime": true}
   {"value": 1167329, "isPrime": true}
   {"value": 1167347, "isPrime": true}
   {"value": 1167349, "isPrime": true}
   {"value": 1167359, "isPrime": true}
   {"value": 1167391, "isPrime": true}
   {"value": 1167409, "isPrime": true}
   {"value": 1167421, "isPrime": true}
   {"value": 1167443, "isPrime": true}
   {"value": 1167449, "isPrime": true}
   {"value": 1167469, "isPrime": true}
   {"value": 1167473, "isPrime": true}
   {"value": 1167539, "isPrime": true}
   {"value": 1167547, "isPrime": true}
   {"value": 1167559, "isPrime": true}
   {"value": 1167571, "isPrime": true}
   {"value": 1167581, "isPrime": true}
   {"value": 1167587, "isPrime": true}
   {"value": 1167599, "isPrime": true}
   {"value": 1167613, "isPrime": true}
   {"value": 1167623, "isPrime": true}
   {"value": 1167637, "isPrime": true}
   {"value": 1167653, "isPrime": true}
   {"value": 1167659, "isPrime": true}
   {"value": 1167667, "isPrime": true}
   {"value": 1167689, "isPrime": true}
   {"value": 1167697, "isPrime": true}
   {"value": 1167701, "isPrime": true}
   {"value": 1167703, "isPrime": true}
   {"value": 1167707, "isPrime": true}
   {"value": 1167709, "isPrime": true}
   {"value": 1167731, "isPrime": true}
   {"value": 1167763, "isPrime": true}
   {"value": 1167773, "isPrime": true}
   {"value": 1167791, "isPrime": true}
   {"value": 1167799, "isPrime": true}
   {"value": 1167811, "isPrime": true}
   {"value": 1167821, "isPrime": true}
   {"value": 1167823, "isPrime": true}
   {"value": 1167833, "isPrime": true}
   {"value": 1167839, "isPrime": true}
   {"value": 1167841, "isPrime": true}
   {"value": 1167847, "isPrime": true}
   {"value": 1167853, "isPrime": true}
   {"value": 1167869, "isPrime": true}
   {"value": 1167889, "isPrime": true}
   {"value": 1167899, "isPrime": true}
   {"value": 1167913, "isPrime": true}
   {"value": 1167919, "isPrime": true}
   {"value": 1167937, "isPrime": true}
   {"value": 1167953, "isPrime": true}
   {"value": 1167973, "isPrime": true}
]
