[
   {"value": 1331023, "isPrime": true},
   {"value": 1331039, "isPrime": true},
   {"value": 1331041, "isPrime": true},
   {"value": 1331051, "isPrime": true},
   {"value": 1331059, "isPrime": true},
   {"value": 1331063, "isPrime": true},
   {"value": 1331093, "isPrime": true},
   {"value": 1331107, "isPrime": true},
   {"value": 1331119, "isPrime": true},
   {"value": 1331123, "isPrime": true},
   {"value": 1331153, "isPrime": true},
   {"value": 1331207, "isPrime": true},
   {"value": 1331227, "isPrime": true},
   {"value": 1331243, "isPrime": true},
   {"value": 1331249, "isPrime": true},
   {"value": 1331251, "isPrime": true},
   {"value": 1331261, "isPrime": true},
   {"value": 1331269, "isPrime": true},
   {"value": 1331279, "isPrime": true},
   {"value": 1331293, "isPrime": true},
   {"value": 1331299, "isPrime": true},
   {"value": 1331327, "isPrime": true},
   {"value": 1331329, "isPrime": true},
   {"value": 1331333, "isPrime": true},
   {"value": 1331339, "isPrime": true},
   {"value": 1331347, "isPrime": true},
   {"value": 1331377, "isPrime": true},
   {"value": 1331381, "isPrime": true},
   {"value": 1331383, "isPrime": true},
   {"value": 1331399, "isPrime": true},
   {"value": 1331411, "isPrime": true},
   {"value": 1331431, "isPrime": true},
   {"value": 1331437, "isPrime": true},
   {"value": 1331443, "isPrime": true},
   {"value": 1331471, "isPrime": true},
   {"value": 1331489, "isPrime": true},
   {"value": 1331497, "isPrime": true},
   {"value": 1331513, "isPrime": true},
   {"value": 1331521, "isPrime": true},
   {"value": 1331527, "isPrime": true},
   {"value": 1331549, "isPrime": true},
   {"value": 1331567, "isPrime": true},
   {"value": 1331573, "isPrime": true},
   {"value": 1331579, "isPrime": true},
   {"value": 1331587, "isPrime": true},
   {"value": 1331591, "isPrime": true},
   {"value": 1331597, "isPrime": true},
   {"value": 1331599, "isPrime": true},
   {"value": 1331611, "isPrime": true},
   {"value": 1331633, "isPrime": true},
   {"value": 1331641, "isPrime": true},
   {"value": 1331647, "isPrime": true},
   {"value": 1331657, "isPrime": true},
   {"value": 1331663, "isPrime": true},
   {"value": 1331683, "isPrime": true},
   {"value": 1331699, "isPrime": true},
   {"value": 1331711, "isPrime": true},
   {"value": 1331719, "isPrime": true},
   {"value": 1331749, "isPrime": true},
   {"value": 1331761, "isPrime": true},
   {"value": 1331773, "isPrime": true},
   {"value": 1331779, "isPrime": true},
   {"value": 1331783, "isPrime": true},
   {"value": 1331789, "isPrime": true},
   {"value": 1331801, "isPrime": true},
   {"value": 1331821, "isPrime": true},
   {"value": 1331851, "isPrime": true},
   {"value": 1331857, "isPrime": true},
   {"value": 1331921, "isPrime": true},
   {"value": 1331923, "isPrime": true},
   {"value": 1331929, "isPrime": true},
   {"value": 1331951, "isPrime": true},
   {"value": 1331959, "isPrime": true},
   {"value": 1331969, "isPrime": true},
   {"value": 1331987, "isPrime": true},
   {"value": 1331989, "isPrime": true}
]
