[
   {"value": 9182003, "isPrime": true}
   {"value": 9182021, "isPrime": true}
   {"value": 9182027, "isPrime": true}
   {"value": 9182039, "isPrime": true}
   {"value": 9182053, "isPrime": true}
   {"value": 9182077, "isPrime": true}
   {"value": 9182081, "isPrime": true}
   {"value": 9182093, "isPrime": true}
   {"value": 9182101, "isPrime": true}
   {"value": 9182113, "isPrime": true}
   {"value": 9182123, "isPrime": true}
   {"value": 9182137, "isPrime": true}
   {"value": 9182153, "isPrime": true}
   {"value": 9182171, "isPrime": true}
   {"value": 9182233, "isPrime": true}
   {"value": 9182281, "isPrime": true}
   {"value": 9182287, "isPrime": true}
   {"value": 9182309, "isPrime": true}
   {"value": 9182323, "isPrime": true}
   {"value": 9182387, "isPrime": true}
   {"value": 9182389, "isPrime": true}
   {"value": 9182447, "isPrime": true}
   {"value": 9182449, "isPrime": true}
   {"value": 9182507, "isPrime": true}
   {"value": 9182519, "isPrime": true}
   {"value": 9182527, "isPrime": true}
   {"value": 9182557, "isPrime": true}
   {"value": 9182561, "isPrime": true}
   {"value": 9182573, "isPrime": true}
   {"value": 9182581, "isPrime": true}
   {"value": 9182599, "isPrime": true}
   {"value": 9182609, "isPrime": true}
   {"value": 9182611, "isPrime": true}
   {"value": 9182627, "isPrime": true}
   {"value": 9182639, "isPrime": true}
   {"value": 9182651, "isPrime": true}
   {"value": 9182653, "isPrime": true}
   {"value": 9182687, "isPrime": true}
   {"value": 9182711, "isPrime": true}
   {"value": 9182713, "isPrime": true}
   {"value": 9182717, "isPrime": true}
   {"value": 9182731, "isPrime": true}
   {"value": 9182741, "isPrime": true}
   {"value": 9182777, "isPrime": true}
   {"value": 9182783, "isPrime": true}
   {"value": 9182801, "isPrime": true}
   {"value": 9182807, "isPrime": true}
   {"value": 9182837, "isPrime": true}
   {"value": 9182843, "isPrime": true}
   {"value": 9182863, "isPrime": true}
   {"value": 9182891, "isPrime": true}
   {"value": 9182903, "isPrime": true}
   {"value": 9182963, "isPrime": true}
   {"value": 9182977, "isPrime": true}
   {"value": 9182981, "isPrime": true}
]
