[
   {"value": 9467047, "isPrime": true},
   {"value": 9467057, "isPrime": true},
   {"value": 9467083, "isPrime": true},
   {"value": 9467119, "isPrime": true},
   {"value": 9467141, "isPrime": true},
   {"value": 9467173, "isPrime": true},
   {"value": 9467177, "isPrime": true},
   {"value": 9467179, "isPrime": true},
   {"value": 9467207, "isPrime": true},
   {"value": 9467233, "isPrime": true},
   {"value": 9467251, "isPrime": true},
   {"value": 9467287, "isPrime": true},
   {"value": 9467291, "isPrime": true},
   {"value": 9467299, "isPrime": true},
   {"value": 9467309, "isPrime": true},
   {"value": 9467321, "isPrime": true},
   {"value": 9467327, "isPrime": true},
   {"value": 9467333, "isPrime": true},
   {"value": 9467347, "isPrime": true},
   {"value": 9467357, "isPrime": true},
   {"value": 9467363, "isPrime": true},
   {"value": 9467371, "isPrime": true},
   {"value": 9467387, "isPrime": true},
   {"value": 9467399, "isPrime": true},
   {"value": 9467407, "isPrime": true},
   {"value": 9467411, "isPrime": true},
   {"value": 9467417, "isPrime": true},
   {"value": 9467441, "isPrime": true},
   {"value": 9467461, "isPrime": true},
   {"value": 9467473, "isPrime": true},
   {"value": 9467519, "isPrime": true},
   {"value": 9467531, "isPrime": true},
   {"value": 9467537, "isPrime": true},
   {"value": 9467581, "isPrime": true},
   {"value": 9467587, "isPrime": true},
   {"value": 9467599, "isPrime": true},
   {"value": 9467603, "isPrime": true},
   {"value": 9467629, "isPrime": true},
   {"value": 9467641, "isPrime": true},
   {"value": 9467677, "isPrime": true},
   {"value": 9467683, "isPrime": true},
   {"value": 9467687, "isPrime": true},
   {"value": 9467699, "isPrime": true},
   {"value": 9467701, "isPrime": true},
   {"value": 9467713, "isPrime": true},
   {"value": 9467747, "isPrime": true},
   {"value": 9467753, "isPrime": true},
   {"value": 9467791, "isPrime": true},
   {"value": 9467873, "isPrime": true},
   {"value": 9467903, "isPrime": true},
   {"value": 9467917, "isPrime": true},
   {"value": 9467951, "isPrime": true},
   {"value": 9467957, "isPrime": true},
   {"value": 9467959, "isPrime": true},
   {"value": 9467981, "isPrime": true},
   {"value": 9467987, "isPrime": true},
   {"value": 9467999, "isPrime": true}
]
