[
   {"value": 9678007, "isPrime": true}
   {"value": 9678013, "isPrime": true}
   {"value": 9678017, "isPrime": true}
   {"value": 9678023, "isPrime": true}
   {"value": 9678029, "isPrime": true}
   {"value": 9678037, "isPrime": true}
   {"value": 9678047, "isPrime": true}
   {"value": 9678061, "isPrime": true}
   {"value": 9678073, "isPrime": true}
   {"value": 9678079, "isPrime": true}
   {"value": 9678131, "isPrime": true}
   {"value": 9678133, "isPrime": true}
   {"value": 9678143, "isPrime": true}
   {"value": 9678181, "isPrime": true}
   {"value": 9678187, "isPrime": true}
   {"value": 9678191, "isPrime": true}
   {"value": 9678197, "isPrime": true}
   {"value": 9678203, "isPrime": true}
   {"value": 9678209, "isPrime": true}
   {"value": 9678233, "isPrime": true}
   {"value": 9678241, "isPrime": true}
   {"value": 9678247, "isPrime": true}
   {"value": 9678259, "isPrime": true}
   {"value": 9678269, "isPrime": true}
   {"value": 9678271, "isPrime": true}
   {"value": 9678299, "isPrime": true}
   {"value": 9678323, "isPrime": true}
   {"value": 9678329, "isPrime": true}
   {"value": 9678341, "isPrime": true}
   {"value": 9678343, "isPrime": true}
   {"value": 9678367, "isPrime": true}
   {"value": 9678379, "isPrime": true}
   {"value": 9678401, "isPrime": true}
   {"value": 9678407, "isPrime": true}
   {"value": 9678439, "isPrime": true}
   {"value": 9678499, "isPrime": true}
   {"value": 9678503, "isPrime": true}
   {"value": 9678509, "isPrime": true}
   {"value": 9678511, "isPrime": true}
   {"value": 9678517, "isPrime": true}
   {"value": 9678521, "isPrime": true}
   {"value": 9678577, "isPrime": true}
   {"value": 9678589, "isPrime": true}
   {"value": 9678611, "isPrime": true}
   {"value": 9678623, "isPrime": true}
   {"value": 9678629, "isPrime": true}
   {"value": 9678637, "isPrime": true}
   {"value": 9678667, "isPrime": true}
   {"value": 9678671, "isPrime": true}
   {"value": 9678679, "isPrime": true}
   {"value": 9678689, "isPrime": true}
   {"value": 9678737, "isPrime": true}
   {"value": 9678743, "isPrime": true}
   {"value": 9678749, "isPrime": true}
   {"value": 9678751, "isPrime": true}
   {"value": 9678761, "isPrime": true}
   {"value": 9678787, "isPrime": true}
   {"value": 9678821, "isPrime": true}
   {"value": 9678833, "isPrime": true}
   {"value": 9678841, "isPrime": true}
   {"value": 9678853, "isPrime": true}
   {"value": 9678857, "isPrime": true}
   {"value": 9678863, "isPrime": true}
   {"value": 9678901, "isPrime": true}
   {"value": 9678947, "isPrime": true}
   {"value": 9678959, "isPrime": true}
   {"value": 9678971, "isPrime": true}
   {"value": 9678973, "isPrime": true}
   {"value": 9678979, "isPrime": true}
]
